pycord/localizer/__init__.py
pycord/localizer/core.py
pycord/localizer/py.typed
pycord/localizer/types.py
pycord/localizer/utils.py
pycord/localizer/i18n/__init__.py
pycord/localizer/i18n/base.py
pycord/localizer/i18n/choice.py
pycord/localizer/i18n/command.py
pycord/localizer/i18n/context.py
pycord_localizer-0.1.3.dist-info/licenses/LICENSE
pycord_localizer-0.1.3.dist-info/METADATA
pycord_localizer-0.1.3.dist-info/WHEEL
pycord_localizer-0.1.3.dist-info/top_level.txt
pycord_localizer-0.1.3.dist-info/RECORD
